{
  "rasa_nlu_data": {
    "entity_synonyms": [],
    "regex_features": [],
    "common_examples": [
      {
        "text": "Hello",
        "entities": [],
        "intent": "greet"
      },
      {
        "text": "goodbye",
        "entities": [],
        "intent": "goodbye"
      },
      {
        "text": "What's the weather in Berlin at the moment?",
        "entities": [
          {
            "value": "Berlin",
            "entity": "location",
            "start": 22,
            "end": 28
          }
        ],
        "intent": "inform"
      },
      {
        "text": "hey",
        "entities": [],
        "intent": "greet"
      },
      {
        "text": "hello",
        "entities": [],
        "intent": "greet"
      },
      {
        "text": "hi",
        "entities": [],
        "intent": "greet"
      },
      {
        "text": "heya",
        "entities": [],
        "intent": "greet"
      },
      {
        "text": "howdy",
        "entities": [],
        "intent": "greet"
      },
      {
        "text": "hey there",
        "entities": [],
        "intent": "greet"
      },
      {
        "text": "bye",
        "entities": [],
        "intent": "goodbye"
      },
      {
        "text": "goodbye",
        "entities": [],
        "intent": "goodbye"
      },
      {
        "text": "bye bye",
        "entities": [],
        "intent": "goodbye"
      },
      {
        "text": "see ya",
        "entities": [],
        "intent": "goodbye"
      },
      {
        "text": "see you later",
        "entities": [],
        "intent": "goodbye"
      },
      {
        "text": "What's the weather today?",
        "entities": [],
        "intent": "inform"
      },
      {
        "text": "What's the weather in London today?",
        "entities": [
          {
            "value": "London",
            "entity": "location",
            "start": 22,
            "end": 28
          }
        ],
        "intent": "inform"
      },
      {
        "text": "Show me what's the weather in Paris",
        "entities": [
          {
            "value": "Paris",
            "entity": "location",
            "start": 30,
            "end": 35
          }
        ],
        "intent": "inform"
      },
      {
        "text": "I wonder what is the weather in Vilnius right now?",
        "entities": [
          {
            "value": "Vilnius",
            "entity": "location",
            "start": 32,
            "end": 39
          }
        ],
        "intent": "inform"
      },
      {
        "text": "what is the weather?",
        "entities": [],
        "intent": "inform"
      },
      {
        "text": "Tell me the weather",
        "entities": [],
        "intent": "inform"
      },
      {
        "text": "Is the weather nice in Barcelona today?",
        "entities": [
          {
            "value": "Barcelona",
            "entity": "location",
            "start": 23,
            "end": 32
          }
        ],
        "intent": "inform"
      },
      {
        "text": "I am going to London today and I wonder what is the weather out there?",
        "entities": [
          {
            "value": "London",
            "entity": "location",
            "start": 14,
            "end": 20
          }
        ],
        "intent": "inform"
      },
      {
        "text": "I am planning my trip to Amsterdam. What is the weather out there?",
        "entities": [
          {
            "value": "Amsterdam",
            "entity": "location",
            "start": 25,
            "end": 34
          }
        ],
        "intent": "inform"
      },
      {
        "text": "Show me the weather in Dublin, please",
        "entities": [
          {
            "value": "Dublin",
            "entity": "location",
            "start": 23,
            "end": 29
          }
        ],
        "intent": "inform"
      },
      {
        "text": "in London",
        "entities": [
          {
            "value": "London",
            "entity": "location",
            "start": 3,
            "end": 9
          }
        ],
        "intent": "inform"
      },
      {
        "text": "Lithuania",
        "entities": [
          {
            "value": "Lithuania",
            "entity": "location",
            "start": 0,
            "end": 9
          }
        ],
        "intent": "inform"
      },
      {
        "text": "Oh, sorry, in Italy",
        "entities": [
          {
            "value": "Italy",
            "entity": "location",
            "start": 14,
            "end": 19
          }
        ],
        "intent": "inform"
      },
      {
        "text": "Tell me the weather in Vilnius",
        "entities": [
          {
            "value": "Vilnius",
            "entity": "location",
            "start": 23,
            "end": 30
          }
        ],
        "intent": "inform"
      },
      {
        "text": "The weather condition in Italy",
        "entities": [
          {
            "value": "Italy",
            "entity": "location",
            "start": 25,
            "end": 30
          }
        ],
        "intent": "inform"
      }
    ]
  }
}